model_converters/__init__.py
model_converters/keras_to_tensorflow.py
model_converters-1.3.0.data/scripts/keras_to_tensorflow
model_converters-1.3.0.dist-info/LICENSE
model_converters-1.3.0.dist-info/METADATA
model_converters-1.3.0.dist-info/WHEEL
model_converters-1.3.0.dist-info/top_level.txt
model_converters-1.3.0.dist-info/RECORD
