Metadata-Version: 2.1
Name: model-converters
Version: 1.3.0
Summary: Tools for converting Keras models for use with other ML frameworks.
Home-page: https://www.triage.com/
Author: Triage Technologies Inc.
Author-email: ai@triage.com
License: UNKNOWN
Platform: UNKNOWN
Requires-Dist: tensorflow (==1.*)
Requires-Dist: Keras (>=2.2.0)
Requires-Dist: h5py
